janet/__init__.py
janet/__main__.py
janet/cli.py
janet/api/__init__.py
janet/api/client.py
janet/api/models.py
janet/api/organizations.py
janet/api/projects.py
janet/api/tickets.py
janet/auth/__init__.py
janet/auth/callback_server.py
janet/auth/oauth_flow.py
janet/auth/token_manager.py
janet/config/__init__.py
janet/config/manager.py
janet/config/models.py
janet/markdown/__init__.py
janet/markdown/generator.py
janet/markdown/yjs_converter.py
janet/sync/__init__.py
janet/sync/file_manager.py
janet/sync/readme_generator.py
janet/sync/sse_watcher.py
janet/sync/sync_engine.py
janet/utils/__init__.py
janet/utils/console.py
janet/utils/errors.py
janet/utils/paths.py
janet_cli-0.3.10.dist-info/licenses/LICENSE
janet_cli-0.3.10.dist-info/METADATA
janet_cli-0.3.10.dist-info/WHEEL
janet_cli-0.3.10.dist-info/entry_points.txt
janet_cli-0.3.10.dist-info/top_level.txt
janet_cli-0.3.10.dist-info/RECORD
