Metadata-Version: 2.4
Name: janet-cli
Version: 0.3.10
Summary: CLI tool to sync Janet AI tickets to local markdown files
Author-email: Janet AI <support@janet-ai.com>
License: MIT
Project-URL: Homepage, https://github.com/janet-ai/janet-cli
Project-URL: Repository, https://github.com/janet-ai/janet-cli
Project-URL: Issues, https://github.com/janet-ai/janet-cli/issues
Keywords: cli,janet,tickets,markdown,sync
Classifier: Development Status :: 3 - Alpha
Classifier: Intended Audience :: Developers
Classifier: License :: OSI Approved :: MIT License
Classifier: Programming Language :: Python :: 3
Classifier: Programming Language :: Python :: 3.8
Classifier: Programming Language :: Python :: 3.9
Classifier: Programming Language :: Python :: 3.10
Classifier: Programming Language :: Python :: 3.11
Classifier: Programming Language :: Python :: 3.12
Requires-Python: >=3.8
License-File: LICENSE
Requires-Dist: typer>=0.12.0
Requires-Dist: httpx>=0.27.0
Requires-Dist: pydantic>=2.0.0
Requires-Dist: pydantic-settings>=2.0.0
Requires-Dist: rich>=13.0.0
Requires-Dist: platformdirs>=4.0.0
Requires-Dist: keyring>=25.0.0
Requires-Dist: python-dateutil>=2.8.0
Requires-Dist: pycrdt>=0.9.0
Requires-Dist: InquirerPy>=0.3.4
Provides-Extra: dev
Requires-Dist: pytest>=8.0.0; extra == "dev"
Requires-Dist: pytest-cov>=4.1.0; extra == "dev"
Requires-Dist: pytest-asyncio>=0.23.0; extra == "dev"
Requires-Dist: httpx-mock>=0.15.0; extra == "dev"
Requires-Dist: black>=24.0.0; extra == "dev"
Requires-Dist: mypy>=1.8.0; extra == "dev"
Requires-Dist: ruff>=0.2.0; extra == "dev"
Dynamic: license-file
